CHANGES.rst
CONTRIBUTORS.rst
LICENSE.txt
MANIFEST.in
README.rst
setup.py
bin/pdf_cropper.py
src/pdfcropper/__init__.py
src/pdfcropper/cropper.py
src/pdfcropper.egg-info/PKG-INFO
src/pdfcropper.egg-info/SOURCES.txt
src/pdfcropper.egg-info/dependency_links.txt
src/pdfcropper.egg-info/not-zip-safe
src/pdfcropper.egg-info/requires.txt
src/pdfcropper.egg-info/top_level.txt