Metadata-Version: 1.1
Name: pdfcropper
Version: 0.1.0
Summary: PDF cropper for edeposit project.
Home-page: https://github.com/edeposit/pdfcropper/
Author: Edeposit team
Author-email: edeposit@email.cz
License: GPL2+
Platform: UNKNOWN
Classifier: Programming Language :: Python :: 2.7
Classifier: License :: OSI Approved :: GNU General Public License v2 or later (GPLv2+)
Classifier: Topic :: Software Development :: Libraries :: Python Modules
